userDevil/__init__.py
userDevil-0.0.1.dist-info/LICENSES.txt
userDevil-0.0.1.dist-info/METADATA
userDevil-0.0.1.dist-info/WHEEL
userDevil-0.0.1.dist-info/top_level.txt
userDevil-0.0.1.dist-info/RECORD
